.foundryrc
.gitignore
.travis.yml
CHANGELOG.rst
LICENSE-MIT
MANIFEST.in
README.rst
release.sh
requirements-dev.txt
requirements.txt
setup.cfg
setup.py
test.sh
email_split/__init__.py
email_split/__init__.pyc
email_split/email_split.pyc
email_split.egg-info/PKG-INFO
email_split.egg-info/SOURCES.txt
email_split.egg-info/dependency_links.txt
email_split.egg-info/top_level.txt
email_split/test/__init__.py
email_split/test/__init__.pyc
email_split/test/test.py
email_split/test/test.pyc