Metadata-Version: 1.1
Name: email-split
Version: 1.0.0
Summary: Split an email address into its local and domain parts
Home-page: https://github.com/underdogio/python-email-split
Author: Todd Wolfson
Author-email: todd@twolfson.com
License: MIT
Download-URL: https://github.com/underdogio/python-email-split/archive/master.zip
Keywords: split,email,parse,local,domain
Platform: UNKNOWN
Classifier: Development Status :: 3 - Alpha
Classifier: Intended Audience :: Developers
Classifier: License :: Public Domain
Classifier: Operating System :: OS Independent
Classifier: Programming Language :: Python
